{
  "cli_version": "0.7.5",
  "checkpoint_id": "d38c65c1d0c8",
  "session_id": "ses_150660b12ffeqSh63tuVY69B2t",
  "strategy": "manual-commit",
  "created_at": "2026-06-11T00:19:44.248536359Z",
  "branch": "main",
  "checkpoints_count": 2,
  "files_touched": [
    "AGENTS.md",
    "CHANGELOG.md",
    "README.md",
    "bin/keating.js",
    "bun.lock",
    "docs/TUTORIAL.md",
    "docs/doctor.tape",
    "docs/improve-flow.tape",
    "docs/intro.tape",
    "docs/learning-flow.tape",
    "docs/session-flow.tape",
    "docs/teacher-flow.tape",
    "docs/tests.tape",
    "justfile",
    "package-lock.json",
    "package.json",
    "packages/browser-agent-runtime/package.json",
    "scripts/generate-nodepod-boot-files.ts",
    "src/cli/main.ts",
    "src/cli/web.ts",
    "src/core/commands.ts",
    "src/pi/hyperteacher-extension.ts",
    "test/package.test.ts",
    "web/index.html",
    "web/package.json",
    "web/src/app.css",
    "web/src/components/AssistantChatPanel.tsx",
    "web/src/components/BootSequence.tsx",
    "web/src/components/ChatIntro.stories.tsx",
    "web/src/components/ChatIntro.tsx",
    "web/src/components/Footer.tsx",
    "web/src/components/JsonCrackBlock.stories.tsx",
    "web/src/components/MarkdownBlock.stories.tsx",
    "web/src/components/MarkdownBlock.tsx",
    "web/src/components/Nav.tsx",
    "web/src/components/QuizResultCard.stories.tsx",
    "web/src/components/SandboxView.tsx",
    "web/src/components/SessionCard.stories.tsx",
    "web/src/components/SessionCard.tsx",
    "web/src/components/SessionManagerDialog.tsx",
    "web/src/components/SessionSidebar.tsx",
    "web/src/components/SettingRow.stories.tsx",
    "web/src/components/Toggle.stories.tsx",
    "web/src/components/UsageCharts.tsx",
    "web/src/components/session-card-visuals.ts",
    "web/src/keating/browser-tools.ts",
    "web/src/keating/core.ts",
    "web/src/keating/export.ts",
    "web/src/keating/nodepod-boot-files.ts",
    "web/src/keating/nodepod-runtime.ts",
    "web/src/keating/storage.ts",
    "web/src/keating/ui-settings.ts",
    "web/src/og-image.tsx",
    "web/src/pages/Blog.tsx",
    "web/src/pages/KeatingBench.tsx",
    "web/src/pages/Landing.tsx",
    "web/src/pages/Paper.tsx",
    "web/src/pages/Tutorial.tsx",
    "web/src/pages/Usage.tsx",
    "web/src/styles/retro.css",
    "web/src/test/export.test.ts",
    "web/src/theme-sync.ts"
  ],
  "agent": "OpenCode",
  "model": "neuralwatt/moonshotai/Kimi-K2.6",
  "turn_id": "eb5f585fae1b",
  "token_usage": {
    "input_tokens": 196504,
    "cache_creation_tokens": 0,
    "cache_read_tokens": 2155200,
    "output_tokens": 16789,
    "api_call_count": 28
  },
  "session_metrics": {
    "turn_count": 2
  },
  "initial_attribution": {
    "calculated_at": "2026-06-11T00:19:44.218046021Z",
    "agent_lines": 2500,
    "agent_removed": 501,
    "human_added": 1233,
    "human_modified": 1139,
    "human_removed": 0,
    "total_committed": 4871,
    "total_lines_changed": 5398,
    "agent_percentage": 55.59466469062616,
    "metric_version": 2
  },
  "prompt_attributions": [
    {
      "checkpoint_number": 1,
      "user_lines_added": 2417,
      "user_lines_removed": 1096,
      "agent_lines_added": 0,
      "agent_lines_removed": 0,
      "user_added_per_file": {
        "AGENTS.md": 3,
        "CHANGELOG.md": 15,
        "README.md": 22,
        "bin/keating.js": 13,
        "bun.lock": 8,
        "docs/TUTORIAL.md": 7,
        "docs/doctor.tape": 1,
        "docs/improve-flow.tape": 3,
        "docs/intro.tape": 1,
        "docs/learning-flow.tape": 3,
        "docs/session-flow.tape": 1,
        "docs/teacher-flow.tape": 2,
        "docs/tests.tape": 1,
        "justfile": 18,
        "package-lock.json": 6,
        "package.json": 2,
        "packages/browser-agent-runtime/package.json": 1,
        "scripts/generate-nodepod-boot-files.ts": 22,
        "scripts/sync-version.ts": 180,
        "src/cli/main.ts": 1,
        "src/cli/web.ts": 1,
        "src/core/commands.ts": 1,
        "src/core/version.ts": 22,
        "src/pi/hyperteacher-extension.ts": 42,
        "test/package.test.ts": 44,
        "web/index.html": 3,
        "web/package.json": 6,
        "web/src/app.css": 126,
        "web/src/components/AssistantChatPanel.tsx": 1,
        "web/src/components/BootSequence.tsx": 1,
        "web/src/components/ChatIntro.tsx": 4,
        "web/src/components/Footer.tsx": 4,
        "web/src/components/Nav.tsx": 7,
        "web/src/components/SandboxView.tsx": 566,
        "web/src/components/SessionCard.stories.tsx": 1,
        "web/src/components/SessionCard.tsx": 2,
        "web/src/components/SessionManagerDialog.tsx": 2,
        "web/src/components/SessionSidebar.tsx": 3,
        "web/src/components/UsageCharts.tsx": 1,
        "web/src/components/session-card-visuals.ts": 1,
        "web/src/keating/browser-tools.ts": 15,
        "web/src/keating/core.ts": 1,
        "web/src/keating/export.ts": 72,
        "web/src/keating/lix-sandbox.ts": 370,
        "web/src/keating/nodepod-boot-files.ts": 75,
        "web/src/keating/nodepod-runtime.ts": 125,
        "web/src/keating/nodepod-snapshot-db.ts": 89,
        "web/src/keating/sandbox-export.ts": 127,
        "web/src/keating/ui-settings.ts": 16,
        "web/src/lib/browser-download.ts": 11,
        "web/src/lib/session-date.ts": 21,
        "web/src/og-image.tsx": 14,
        "web/src/pages/Blog.tsx": 17,
        "web/src/pages/KeatingBench.tsx": 2,
        "web/src/pages/Landing.tsx": 25,
        "web/src/pages/Paper.tsx": 3,
        "web/src/pages/Tutorial.tsx": 79,
        "web/src/pages/Usage.tsx": 3,
        "web/src/styles/retro.css": 144,
        "web/src/test/export.test.ts": 36,
        "web/src/test/nodepod-transpile.test.ts": 22,
        "web/src/theme-sync.ts": 2
      },
      "user_removed_per_file": {
        "README.md": 20,
        "bin/keating.js": 1,
        "bun.lock": 329,
        "docs/TUTORIAL.md": 7,
        "docs/doctor.tape": 1,
        "docs/improve-flow.tape": 3,
        "docs/intro.tape": 1,
        "docs/learning-flow.tape": 3,
        "docs/session-flow.tape": 1,
        "docs/teacher-flow.tape": 2,
        "docs/tests.tape": 1,
        "justfile": 2,
        "package-lock.json": 15,
        "package.json": 1,
        "packages/browser-agent-runtime/package.json": 1,
        "scripts/generate-nodepod-boot-files.ts": 17,
        "src/cli/main.ts": 2,
        "src/cli/web.ts": 1,
        "src/pi/hyperteacher-extension.ts": 35,
        "web/index.html": 3,
        "web/package.json": 2,
        "web/src/app.css": 96,
        "web/src/components/AssistantChatPanel.tsx": 1,
        "web/src/components/BootSequence.tsx": 1,
        "web/src/components/ChatIntro.tsx": 4,
        "web/src/components/Footer.tsx": 4,
        "web/src/components/Nav.tsx": 7,
        "web/src/components/SandboxView.tsx": 128,
        "web/src/components/SessionCard.stories.tsx": 1,
        "web/src/components/SessionCard.tsx": 13,
        "web/src/components/SessionManagerDialog.tsx": 11,
        "web/src/components/SessionSidebar.tsx": 12,
        "web/src/components/UsageCharts.tsx": 1,
        "web/src/components/session-card-visuals.ts": 1,
        "web/src/keating/browser-tools.ts": 8,
        "web/src/keating/core.ts": 1,
        "web/src/keating/export.ts": 2,
        "web/src/keating/nodepod-boot-files.ts": 67,
        "web/src/keating/nodepod-runtime.ts": 58,
        "web/src/keating/ui-settings.ts": 5,
        "web/src/og-image.tsx": 14,
        "web/src/pages/Blog.tsx": 17,
        "web/src/pages/KeatingBench.tsx": 13,
        "web/src/pages/Landing.tsx": 25,
        "web/src/pages/Paper.tsx": 3,
        "web/src/pages/Tutorial.tsx": 79,
        "web/src/pages/Usage.tsx": 13,
        "web/src/styles/retro.css": 61,
        "web/src/theme-sync.ts": 2
      }
    },
    {
      "checkpoint_number": 2,
      "user_lines_added": 467,
      "user_lines_removed": 42,
      "agent_lines_added": 2858,
      "agent_lines_removed": 1096,
      "user_added_per_file": {
        "web/src/keating/nodepod-boot-files.ts": 5,
        "web/src/keating/portable-data.ts": 101,
        "web/src/keating/storage.ts": 252,
        "web/src/pages/Usage.tsx": 109
      },
      "user_removed_per_file": {
        "web/src/keating/nodepod-boot-files.ts": 3,
        "web/src/keating/storage.ts": 38,
        "web/src/pages/Usage.tsx": 1
      }
    }
  ]
}
